Metadata-Version: 2.0
Name: odoo10-addon-website-sale-suggest-create-account
Version: 10.0.1.1.0
Summary: Suggest users to create an account when buying in the website
Home-page: https://www.tecnativa.com
Author: Tecnativa, LasLabs, Odoo Community Association (OCA)
Author-email: support@odoo-community.org
License: LGPL-3
Platform: UNKNOWN
Classifier: Programming Language :: Python
Classifier: Framework :: Odoo
Classifier: License :: OSI Approved :: GNU Lesser General Public License v3 (LGPLv3)
Requires-Python: ~=2.7
Requires-Dist: odoo (<10.1dev,>=10.0)
